src/Alert_System.py
src/__init__.py
ExamProctoringTool-0.1.0.dist-info/METADATA
ExamProctoringTool-0.1.0.dist-info/WHEEL
ExamProctoringTool-0.1.0.dist-info/top_level.txt
ExamProctoringTool-0.1.0.dist-info/RECORD
