Metadata-Version: 2.1
Name: ExamProctoringTool
Version: 0.1.0
Summary: ExamProctoringTool
Home-page: https://github.com/yuta0726/ExamProctoringTool
Author: yuta morimoto
Author-email: s2222081@stu.musashino-u.ac.jp
Requires-Python: >=3.12.3
